{
  "generated_at": "2025-12-14T14:22:53.892970",
  "counties": {
    "total": 5,
    "biggest_increase": {
      "name": "Duval",
      "change": 0.0
    },
    "biggest_decrease": {
      "name": "Nassau",
      "change": 0.0
    }
  },
  "schools": {
    "total": 132,
    "biggest_increase": {
      "name": "Robert E. Lee High School",
      "county": "Duval",
      "change": 0.0
    },
    "biggest_decrease": {
      "name": "Bryceville Elementary School",
      "county": "Nassau",
      "change": 0.0
    }
  }
}